fancy_subprocess/__init__.py
fancy_subprocess/_compat.py
fancy_subprocess/_print.py
fancy_subprocess/_reconfigure.py
fancy_subprocess/_run_core.py
fancy_subprocess/_run_param.py
fancy_subprocess/_run_wrappers.py
fancy_subprocess/_utils.py
fancy_subprocess/py.typed
fancy_subprocess-2.3.dist-info/METADATA
fancy_subprocess-2.3.dist-info/WHEEL
fancy_subprocess-2.3.dist-info/licenses/LICENSE
fancy_subprocess-2.3.dist-info/RECORD
