Metadata-Version: 2.4
Name: fancy-subprocess
Version: 2.3
Summary: subprocess.run() with formatted output, detailed error messages and retry capabilities
Project-URL: Homepage, https://github.com/petamas/python-fancy-subprocess
Project-URL: Bug Tracker, https://github.com/petamas/python-fancy-subprocess/issues
Author-email: Tamás PEREGI <petamas@gmail.com>
License-Expression: MIT
License-File: LICENSE
Classifier: License :: OSI Approved :: MIT License
Classifier: Operating System :: MacOS
Classifier: Operating System :: Microsoft :: Windows
Classifier: Operating System :: OS Independent
Classifier: Operating System :: POSIX
Classifier: Programming Language :: Python :: 3
Classifier: Programming Language :: Python :: 3.10
Classifier: Programming Language :: Python :: 3.11
Classifier: Programming Language :: Python :: 3.12
Classifier: Programming Language :: Python :: 3.13
Requires-Python: >=3.10
Requires-Dist: ntstatus<3,>=2.0
Requires-Dist: oslex<2,>=0.1.3
Requires-Dist: pathext<2,>=1.5
Requires-Dist: typeguard<5,>=4.4.2
Requires-Dist: typing-extensions<5,>=4.14
